{
  "id": "fr_to_de_A1__transportation",
  "source": "fr",
  "target": "de",
  "group": "A1__transportation",
  "words": [
    {
      "base_word": "bicycle",
      "source_word": "vélo",
      "target_word": "Fahrrad",
      "source_phonetic": "/velo/",
      "target_phonetic": "/ˈfaːɐ̯ˌʁaːt/",
      "source_example": "Il est monté sur son vélo et est parti.",
      "target_example": "Er stieg auf sein Fahrrad und fuhr los.",
      "topic": "transportation",
      "level": "A1"
    },
    {
      "base_word": "bike",
      "source_word": "vélo",
      "target_word": "Fahrrad",
      "source_phonetic": "/velo/",
      "target_phonetic": "/ˈfaːɐ̯ˌʁaːt/",
      "source_example": "Je vais au travail en vélo.",
      "target_example": "Ich fahre mit dem Fahrrad zur Arbeit.",
      "topic": "transportation",
      "level": "A1"
    },
    {
      "base_word": "boat",
      "source_word": "bateau",
      "target_word": "Boot",
      "source_phonetic": "/bato/",
      "target_phonetic": "/boːt/",
      "source_example": "Nous avons fait une promenade en bateau.",
      "target_example": "Wir machten eine Bootstour.",
      "topic": "transportation",
      "level": "A1"
    },
    {
      "base_word": "bus",
      "source_word": "bus",
      "target_word": "Bus",
      "source_phonetic": "/bys/",
      "target_phonetic": "/bʊs/",
      "source_example": "Je vais au travail en bus.",
      "target_example": "Ich fahre mit dem Bus zur Arbeit.",
      "topic": "transportation",
      "level": "A1"
    },
    {
      "base_word": "car",
      "source_word": "voiture",
      "target_word": "Auto",
      "source_phonetic": "/vwa.tyʁ/",
      "target_phonetic": "/ˈaʊto/",
      "source_example": "Paula est montée dans la voiture et est partie.",
      "target_example": "Paula stieg ins Auto und fuhr los.",
      "topic": "transportation",
      "level": "A1"
    },
    {
      "base_word": "drive",
      "source_word": "conduire",
      "target_word": "fahren",
      "source_phonetic": "/kɔ̃.dɥiʁ/",
      "target_phonetic": "/ˈfaːʁən/",
      "source_example": "Sais-tu conduire ?",
      "target_example": "Kannst du Auto fahren?",
      "topic": "transportation",
      "level": "A1"
    },
    {
      "base_word": "driver",
      "source_word": "conducteur",
      "target_word": "Fahrer",
      "source_phonetic": "/kɔ̃.dyk.tœʁ/",
      "target_phonetic": "/ˈfaːʁɐ/",
      "source_example": "C'est une bonne conductrice.",
      "target_example": "Sie ist eine gute Fahrerin.",
      "topic": "transportation",
      "level": "A1"
    }
  ]
}